{
    "0": {
        "column_swaps": [[1, 4], [0, 3]],
        "css_column_swaps": [[1, 4], [0, 3], [0, 3], [1, 4]],
        "css_form": ["iiixi", "iiiix"],
        "css_gottesman_form": ["xiiii", "ixiii"],
        "css_logicals": ["iixii", "iiixi", "iiiix", "iizii", "iiizi", "iiiiz"],
        "d": 1,
        "gottesman_form": ["xiiii", "ixiii"],
        "graph_state": ["xiiii", "ixiii", "iixii", "iiixi", "iiiix"],
        "group_size_1": 10368.0,
        "group_size_2": 0,
        "is_css": 1,
        "is_decomposable": 1,
        "is_degenerate": 0,
        "is_gf4linear": 0,
        "is_tanner_planar": 1,
        "k": 3,
        "linear_code": ["00100", "01000", "10000"],
        "logicals": ["iixii", "iiixi", "iiiix", "iizii", "iiizi", "iiiiz"],
        "low_weight_form": ["xiiii", "ixiii"],
        "n": 5,
        "stabilizer": ["iiixi", "iiiix"],
        "weight_enumerator": [1, 2, 1, 0, 0, 0]
    },
    "1": {
        "column_swaps": [[1, 4], [0, 2]],
        "css_column_swaps": [[1, 4], [0, 2], [0, 2], [1, 4]],
        "css_form": ["iixxi", "iiiix"],
        "css_gottesman_form": ["xiixi", "ixiii"],
        "css_logicals": ["iixii", "iiixi", "iiiix", "iizii", "ziizi", "iiiiz"],
        "d": 1,
        "gottesman_form": ["xiixi", "ixiii"],
        "graph_state": ["xiiii", "ixiii", "iixii", "iiixi", "iiiix"],
        "group_size_1": 1152.0,
        "group_size_2": 0,
        "is_css": 1,
        "is_decomposable": 1,
        "is_degenerate": 0,
        "is_gf4linear": 0,
        "is_tanner_planar": 1,
        "k": 3,
        "linear_code": ["00110", "01000", "10000"],
        "logicals": ["iixii", "iiixi", "iiiix", "iizii", "ziizi", "iiiiz"],
        "low_weight_form": ["ixiii", "xxixi"],
        "n": 5,
        "stabilizer": ["iixxi", "iiiix"],
        "weight_enumerator": [1, 1, 1, 1, 0, 0]
    },
    "10": {
        "column_swaps": [[1, 4], [0, 1]],
        "css_column_swaps": [],
        "css_form": ["izzzz", "xxiix"],
        "css_gottesman_form": ["xxiix", "izzzz"],
        "css_logicals": ["ixxii", "ixixi", "ixiix", "iizii", "iiizi", "ziiiz"],
        "d": 1,
        "gottesman_form": ["xzzxi", "zxiiz"],
        "graph_state": ["xiiiz", "ixiiz", "iixzi", "iizxi", "zziix"],
        "group_size_1": 32.0,
        "group_size_2": 0,
        "is_css": 1,
        "is_decomposable": 0,
        "is_degenerate": 0,
        "is_gf4linear": 0,
        "is_tanner_planar": 1,
        "k": 3,
        "linear_code": ["01010", "00100", "10000"],
        "logicals": ["zixii", "iiixi", "iziix", "iizii", "ziizi", "iiiiz"],
        "low_weight_form": ["xxiix", "izzzz"],
        "n": 5,
        "stabilizer": ["ixzxz", "zziix"],
        "weight_enumerator": [1, 0, 0, 1, 1, 1]
    },
    "11": {
        "column_swaps": [[1, 3], [0, 2]],
        "css_column_swaps": [[1, 3], [0, 2], [0, 2]],
        "css_form": ["iizzi", "iixxi"],
        "css_gottesman_form": ["xxiii", "zziii"],
        "css_logicals": ["iixii", "iiixi", "iiiix", "iizii", "iiizi", "iiiiz"],
        "d": 1,
        "gf4linear_column_swaps": [[1, 3], [0, 2]],
        "gf4linear_form": ["iiyzi", "iizxi"],
        "gf4linear_gottesman_form": ["yziii", "zxiii"],
        "gf4linear_logicals": ["iixii", "iiixi", "iiiix", "iizii", "iiizi", "iiiiz"],
        "gottesman_form": ["xziii", "zxiii"],
        "graph_state": ["xiiiz", "ixiiz", "iixzi", "iizxi", "zziix"],
        "group_size_1": 15552.0,
        "group_size_2": 0,
        "is_css": 1,
        "is_decomposable": 0,
        "is_degenerate": 0,
        "is_gf4linear": 1,
        "is_tanner_planar": 1,
        "k": 3,
        "linear_code": ["00001", "01000", "10000"],
        "logicals": ["iixii", "iiixi", "iiiix", "iizii", "iiizi", "iiiiz"],
        "low_weight_form": ["xxiii", "zziii"],
        "n": 5,
        "stabilizer": ["iixzi", "iizxi"],
        "weight_enumerator": [1, 0, 3, 0, 0, 0]
    },
    "12": {
        "column_swaps": [[1, 3], [0, 2]],
        "css_column_swaps": [[1, 2], [0, 1], [0, 1]],
        "css_form": ["iizzz", "ixxxi"],
        "css_gottesman_form": ["xxixi", "izizz"],
        "css_logicals": ["iixii", "ixixi", "ixiix", "iizii", "ziizi", "iiiiz"],
        "d": 1,
        "gottesman_form": ["xziiz", "zxizi"],
        "graph_state": ["xiiiz", "ixizz", "iixzz", "izzxi", "zzzix"],
        "group_size_1": 96.0,
        "group_size_2": 0,
        "is_css": 1,
        "is_decomposable": 0,
        "is_degenerate": 0,
        "is_gf4linear": 0,
        "is_tanner_planar": 1,
        "k": 3,
        "linear_code": ["00001", "01000", "10000"],
        "logicals": ["iixii", "izixi", "ziiix", "iizii", "iiizi", "iiiiz"],
        "low_weight_form": ["xxixi", "izizz"],
        "n": 5,
        "stabilizer": ["iixzz", "izzxi"],
        "weight_enumerator": [1, 0, 0, 2, 1, 0]
    },
    "13": {
        "column_swaps": [[1, 3], [0, 1]],
        "css_column_swaps": [[0, 2], [0, 2]],
        "css_form": ["izzzz", "iixxi"],
        "css_gottesman_form": ["xiixi", "zzizz"],
        "css_logicals": ["iixii", "ixixi", "ixiix", "iizii", "ziizi", "iiiiz"],
        "d": 1,
        "gottesman_form": ["xzxiz", "ixzii"],
        "graph_state": ["xiiiz", "ixiiz", "iixzi", "iizxi", "zziix"],
        "group_size_1": 192.0,
        "group_size_2": 0,
        "is_css": 1,
        "is_decomposable": 0,
        "is_degenerate": 0,
        "is_gf4linear": 0,
        "is_tanner_planar": 1,
        "k": 3,
        "linear_code": ["00001", "01100", "10000"],
        "logicals": ["izxii", "iiixi", "ziiix", "zizii", "iiizi", "iiiiz"],
        "low_weight_form": ["xiixi", "zzizz"],
        "n": 5,
        "stabilizer": ["ixxzz", "iizxi"],
        "weight_enumerator": [1, 0, 1, 0, 2, 0]
    },
    "14": {
        "column_swaps": [[1, 3], [0, 2]],
        "css_column_swaps": [[1, 2]],
        "css_form": ["iizzi", "xxxxx"],
        "css_gottesman_form": ["xxxxx", "izizi"],
        "css_logicals": ["iixii", "ixixi", "iiiix", "zizii", "ziizi", "ziiiz"],
        "d": 1,
        "gottesman_form": ["xzzzx", "zxiii"],
        "graph_state": ["xiiiz", "ixiiz", "iixzi", "iizxi", "zziix"],
        "group_size_1": 192.0,
        "group_size_2": 0,
        "is_css": 1,
        "is_decomposable": 0,
        "is_degenerate": 0,
        "is_gf4linear": 0,
        "is_tanner_planar": 1,
        "k": 3,
        "linear_code": ["00101", "01000", "10000"],
        "logicals": ["zixii", "ziixi", "iiiix", "iizii", "iiizi", "ziiiz"],
        "low_weight_form": ["izizi", "xyxyx"],
        "n": 5,
        "stabilizer": ["iizxi", "zzxzx"],
        "weight_enumerator": [1, 0, 1, 0, 0, 2]
    },
    "15": {
        "column_swaps": [],
        "d": 1,
        "gottesman_form": ["xixzz", "ixzxz"],
        "graph_state": ["xiiiz", "ixiiz", "iixzi", "iizxi", "zziix"],
        "group_size_1": 96.0,
        "group_size_2": 0,
        "is_css": 0,
        "is_decomposable": 0,
        "is_degenerate": 0,
        "is_gf4linear": 0,
        "is_tanner_planar": 1,
        "k": 3,
        "linear_code": ["00001", "01010", "10100"],
        "logicals": ["izxii", "ziixi", "zziix", "zizii", "izizi", "iiiiz"],
        "low_weight_form": ["xixzz", "ixzxz"],
        "n": 5,
        "stabilizer": ["xixzz", "ixzxz"],
        "weight_enumerator": [1, 0, 0, 0, 3, 0]
    },
    "16": {
        "column_swaps": [[1, 4]],
        "css_column_swaps": [],
        "css_form": ["zzziz", "xxxix"],
        "css_gottesman_form": ["xxxix", "zzziz"],
        "css_logicals": ["ixxii", "iiixi", "ixiix", "zizii", "iiizi", "ziiiz"],
        "d": 1,
        "gf4linear_column_swaps": [[1, 4]],
        "gf4linear_form": ["yyyiz", "zzzix"],
        "gf4linear_gottesman_form": ["yzyiy", "zxziz"],
        "gf4linear_logicals": ["zzxii", "iiixi", "zziix", "zizii", "iiizi", "ziiiz"],
        "gottesman_form": ["xzxix", "zxziz"],
        "graph_state": ["xiiiz", "ixizz", "iixzz", "izzxi", "zzzix"],
        "group_size_1": 864.0,
        "group_size_2": 0,
        "is_css": 1,
        "is_decomposable": 0,
        "is_degenerate": 0,
        "is_gf4linear": 1,
        "is_tanner_planar": 1,
        "k": 3,
        "linear_code": ["00010", "10100", "11000"],
        "logicals": ["izxii", "iiixi", "iziix", "zizii", "iiizi", "ziiiz"],
        "low_weight_form": ["xxxix", "zzziz"],
        "n": 5,
        "stabilizer": ["xxxiz", "zzzix"],
        "weight_enumerator": [1, 0, 0, 0, 3, 0]
    },
    "17": {
        "column_swaps": [[1, 4], [0, 1]],
        "css_column_swaps": [],
        "css_form": ["iziiz", "xxiix"],
        "css_gottesman_form": ["xxiix", "iziiz"],
        "css_logicals": ["iixii", "iiixi", "ixiix", "iizii", "iiizi", "ziiiz"],
        "d": 1,
        "gottesman_form": ["xziii", "zxiiz"],
        "graph_state": ["xiiiz", "ixiiz", "iixzi", "iizxi", "zziix"],
        "group_size_1": 576.0,
        "group_size_2": 0,
        "is_css": 1,
        "is_decomposable": 0,
        "is_degenerate": 0,
        "is_gf4linear": 0,
        "is_tanner_planar": 1,
        "k": 3,
        "linear_code": ["00010", "00100", "10000"],
        "logicals": ["iixii", "iiixi", "iziix", "iizii", "iiizi", "iiiiz"],
        "low_weight_form": ["iziiz", "xyiiy"],
        "n": 5,
        "stabilizer": ["ixiiz", "zziix"],
        "weight_enumerator": [1, 0, 1, 2, 0, 0]
    },
    "18": {
        "column_swaps": [[1, 3], [0, 1]],
        "css_column_swaps": [],
        "css_form": ["izzzz", "xxxxx"],
        "css_gottesman_form": ["xxxxx", "izzzz"],
        "css_logicals": ["ixxii", "ixixi", "ixiix", "zizii", "ziizi", "ziiiz"],
        "d": 1,
        "gottesman_form": ["xzxiz", "zxzzx"],
        "graph_state": ["xiiiz", "ixiiz", "iixzi", "iizxi", "zziix"],
        "group_size_1": 96.0,
        "group_size_2": 0,
        "is_css": 1,
        "is_decomposable": 0,
        "is_degenerate": 0,
        "is_gf4linear": 0,
        "is_tanner_planar": 1,
        "k": 3,
        "linear_code": ["00011", "01100", "10000"],
        "logicals": ["izxii", "izixi", "ziiix", "zizii", "iiizi", "iziiz"],
        "low_weight_form": ["izzzz", "xyyyy"],
        "n": 5,
        "stabilizer": ["ixxzz", "zzzxx"],
        "weight_enumerator": [1, 0, 0, 0, 1, 2]
    },
    "2": {
        "column_swaps": [],
        "css_column_swaps": [],
        "css_form": ["ziiiz", "iziiz"],
        "css_gottesman_form": ["ziiiz", "iziiz"],
        "css_logicals": ["iixii", "iiixi", "xxiix", "iizii", "iiizi", "iiiiz"],
        "d": 1,
        "gottesman_form": ["xiiiz", "ixiiz"],
        "graph_state": ["xiiiz", "ixiiz", "iixzi", "iizxi", "zziix"],
        "group_size_1": 3456.0,
        "group_size_2": 0,
        "is_css": 1,
        "is_decomposable": 0,
        "is_degenerate": 0,
        "is_gf4linear": 0,
        "is_tanner_planar": 1,
        "k": 3,
        "linear_code": ["00001", "00010", "00100"],
        "logicals": ["iixii", "iiixi", "zziix", "iizii", "iiizi", "iiiiz"],
        "low_weight_form": ["ziiiz", "iziiz"],
        "n": 5,
        "stabilizer": ["xiiiz", "ixiiz"],
        "weight_enumerator": [1, 0, 3, 0, 0, 0]
    },
    "3": {
        "column_swaps": [[1, 4], [0, 1]],
        "css_column_swaps": [[1, 4], [0, 1], [0, 1], [1, 4]],
        "css_form": ["ixxxi", "iiiix"],
        "css_gottesman_form": ["xixxi", "ixiii"],
        "css_logicals": ["iixii", "iiixi", "iiiix", "zizii", "ziizi", "iiiiz"],
        "d": 1,
        "gottesman_form": ["xixxi", "ixiii"],
        "graph_state": ["xiiii", "ixiii", "iixii", "iiixi", "iiiix"],
        "group_size_1": 576.0,
        "group_size_2": 0,
        "is_css": 1,
        "is_decomposable": 1,
        "is_degenerate": 0,
        "is_gf4linear": 0,
        "is_tanner_planar": 1,
        "k": 3,
        "linear_code": ["01010", "01100", "10000"],
        "logicals": ["iixii", "iiixi", "iiiix", "zizii", "ziizi", "iiiiz"],
        "low_weight_form": ["ixiii", "xxxxi"],
        "n": 5,
        "stabilizer": ["ixxxi", "iiiix"],
        "weight_enumerator": [1, 1, 0, 1, 1, 0]
    },
    "4": {
        "column_swaps": [[1, 3], [0, 1]],
        "css_column_swaps": [[0, 2], [0, 2]],
        "css_form": ["iziiz", "iixxi"],
        "css_gottesman_form": ["xiixi", "iziiz"],
        "css_logicals": ["iixii", "iiixi", "ixiix", "iizii", "ziizi", "iiiiz"],
        "d": 1,
        "gottesman_form": ["xiiiz", "ixzii"],
        "graph_state": ["xiiiz", "ixiiz", "iixzi", "iizxi", "zziix"],
        "group_size_1": 768.0,
        "group_size_2": 0,
        "is_css": 1,
        "is_decomposable": 1,
        "is_degenerate": 0,
        "is_gf4linear": 0,
        "is_tanner_planar": 1,
        "k": 3,
        "linear_code": ["00001", "00100", "10000"],
        "logicals": ["izxii", "iiixi", "ziiix", "iizii", "iiizi", "iiiiz"],
        "low_weight_form": ["xiixi", "iziiz"],
        "n": 5,
        "stabilizer": ["ixiiz", "iizxi"],
        "weight_enumerator": [1, 0, 2, 0, 1, 0]
    },
    "5": {
        "column_swaps": [[1, 2], [0, 1]],
        "css_column_swaps": [[1, 2], [0, 1]],
        "css_form": ["izizz", "iizzz"],
        "css_gottesman_form": ["ziizz", "izizz"],
        "css_logicals": ["iixii", "xxixi", "xxiix", "iizii", "iiizi", "iiiiz"],
        "d": 1,
        "gottesman_form": ["xiizz", "ixizz"],
        "graph_state": ["xiiiz", "ixizz", "iixzz", "izzxi", "zzzix"],
        "group_size_1": 384.0,
        "group_size_2": 0,
        "is_css": 1,
        "is_decomposable": 0,
        "is_degenerate": 0,
        "is_gf4linear": 0,
        "is_tanner_planar": 1,
        "k": 3,
        "linear_code": ["00001", "00010", "10000"],
        "logicals": ["iixii", "zzixi", "zziix", "iizii", "iiizi", "iiiiz"],
        "low_weight_form": ["zziii", "izizz"],
        "n": 5,
        "stabilizer": ["ixizz", "iixzz"],
        "weight_enumerator": [1, 0, 1, 2, 0, 0]
    },
    "6": {
        "column_swaps": [[1, 4]],
        "css_column_swaps": [[1, 4], [1, 4]],
        "css_form": ["xxxxi", "iiiix"],
        "css_gottesman_form": ["xixxx", "ixiii"],
        "css_logicals": ["iixii", "iiixi", "iiiix", "zizii", "ziizi", "ziiiz"],
        "d": 1,
        "gottesman_form": ["xixxx", "ixiii"],
        "graph_state": ["xiiii", "ixiii", "iixii", "iiixi", "iiiix"],
        "group_size_1": 768.0,
        "group_size_2": 0,
        "is_css": 1,
        "is_decomposable": 1,
        "is_degenerate": 0,
        "is_gf4linear": 0,
        "is_tanner_planar": 1,
        "k": 3,
        "linear_code": ["10010", "10100", "11000"],
        "logicals": ["iixii", "iiixi", "iiiix", "zizii", "ziizi", "ziiiz"],
        "low_weight_form": ["ixiii", "xxxxx"],
        "n": 5,
        "stabilizer": ["xxxxi", "iiiix"],
        "weight_enumerator": [1, 1, 0, 0, 1, 1]
    },
    "7": {
        "column_swaps": [[1, 4], [0, 3]],
        "css_column_swaps": [],
        "css_form": ["ixxxi", "xxxix"],
        "css_gottesman_form": ["xiixx", "ixxxi"],
        "css_logicals": ["iixii", "iiixi", "iiiix", "izzii", "zzizi", "ziiiz"],
        "d": 1,
        "gottesman_form": ["xiziz", "ixzzz"],
        "graph_state": ["xiiiz", "ixizz", "iixzz", "izzxi", "zzzix"],
        "group_size_1": 256.0,
        "group_size_2": 0,
        "is_css": 1,
        "is_decomposable": 0,
        "is_degenerate": 0,
        "is_gf4linear": 0,
        "is_tanner_planar": 1,
        "k": 3,
        "linear_code": ["00100", "01000", "10000"],
        "logicals": ["zzxii", "izixi", "zziix", "iizii", "iiizi", "iiiiz"],
        "low_weight_form": ["xiixx", "ixxxi"],
        "n": 5,
        "stabilizer": ["izzxi", "zzzix"],
        "weight_enumerator": [1, 0, 0, 2, 1, 0]
    },
    "8": {
        "column_swaps": [[1, 4], [0, 3]],
        "css_column_swaps": [[1, 2], [1, 2]],
        "css_form": ["iixxi", "xxiix"],
        "css_gottesman_form": ["xixix", "ixixi"],
        "css_logicals": ["iixii", "iiixi", "iiiix", "zizii", "izizi", "ziiiz"],
        "d": 1,
        "gottesman_form": ["xizii", "ixizz"],
        "graph_state": ["xiiiz", "ixiiz", "iixzi", "iizxi", "zziix"],
        "group_size_1": 384.0,
        "group_size_2": 0,
        "is_css": 1,
        "is_decomposable": 1,
        "is_degenerate": 0,
        "is_gf4linear": 0,
        "is_tanner_planar": 1,
        "k": 3,
        "linear_code": ["00100", "01000", "10000"],
        "logicals": ["zixii", "izixi", "iziix", "iizii", "iiizi", "iiiiz"],
        "low_weight_form": ["ixixi", "xxxxx"],
        "n": 5,
        "stabilizer": ["iizxi", "zziix"],
        "weight_enumerator": [1, 0, 1, 1, 0, 1]
    },
    "9": {
        "column_swaps": [],
        "css_column_swaps": [],
        "css_form": ["iziiz", "zizzz"],
        "css_gottesman_form": ["zizzz", "iziiz"],
        "css_logicals": ["xixii", "xiixi", "xxiix", "iizii", "iiizi", "iiiiz"],
        "d": 1,
        "gottesman_form": ["xizxz", "ixiiz"],
        "graph_state": ["xiiiz", "ixiiz", "iixzi", "iizxi", "zziix"],
        "group_size_1": 384.0,
        "group_size_2": 0,
        "is_css": 1,
        "is_decomposable": 0,
        "is_degenerate": 0,
        "is_gf4linear": 0,
        "is_tanner_planar": 1,
        "k": 3,
        "linear_code": ["00001", "10010", "00100"],
        "logicals": ["zixii", "iiixi", "zziix", "iizii", "ziizi", "iiiiz"],
        "low_weight_form": ["iziiz", "zzzzi"],
        "n": 5,
        "stabilizer": ["ixiiz", "xizxz"],
        "weight_enumerator": [1, 0, 1, 0, 2, 0]
    }
}
