{
    "0": {
        "column_swaps": [],
        "css_column_swaps": [],
        "css_form": ["xxiiii"],
        "css_gottesman_form": ["xxiiii"],
        "css_logicals": ["ixiiii", "iixiii", "iiixii", "iiiixi", "iiiiix", "zziiii", "iiziii", "iiizii", "iiiizi", "iiiiiz"],
        "d": 1,
        "gottesman_form": ["xxiiii"],
        "graph_state": ["i"],
        "group_size_1": 248832.0,
        "group_size_2": 0,
        "is_css": 1,
        "is_decomposable": 0,
        "is_degenerate": 0,
        "is_gf4linear": 0,
        "is_tanner_planar": 1,
        "k": 5,
        "linear_code": ["0"],
        "logicals": ["ixiiii", "iixiii", "iiixii", "iiiixi", "iiiiix", "zziiii", "iiziii", "iiizii", "iiiizi", "iiiiiz"],
        "low_weight_form": ["xxiiii"],
        "n": 6,
        "stabilizer": ["xxiiii"],
        "weight_enumerator": [1, 0, 1, 0, 0, 0, 0]
    },
    "1": {
        "column_swaps": [],
        "css_column_swaps": [],
        "css_form": ["xxxiii"],
        "css_gottesman_form": ["xxxiii"],
        "css_logicals": ["ixiiii", "iixiii", "iiixii", "iiiixi", "iiiiix", "zziiii", "ziziii", "iiizii", "iiiizi", "iiiiiz"],
        "d": 1,
        "gottesman_form": ["xxxiii"],
        "graph_state": ["i"],
        "group_size_1": 62208.0,
        "group_size_2": 0,
        "is_css": 1,
        "is_decomposable": 0,
        "is_degenerate": 0,
        "is_gf4linear": 0,
        "is_tanner_planar": 1,
        "k": 5,
        "linear_code": ["0"],
        "logicals": ["ixiiii", "iixiii", "iiixii", "iiiixi", "iiiiix", "zziiii", "ziziii", "iiizii", "iiiizi", "iiiiiz"],
        "low_weight_form": ["xxxiii"],
        "n": 6,
        "stabilizer": ["xxxiii"],
        "weight_enumerator": [1, 0, 0, 1, 0, 0, 0]
    },
    "2": {
        "column_swaps": [],
        "css_column_swaps": [],
        "css_form": ["xxxxii"],
        "css_gottesman_form": ["xxxxii"],
        "css_logicals": ["ixiiii", "iixiii", "iiixii", "iiiixi", "iiiiix", "zziiii", "ziziii", "ziizii", "iiiizi", "iiiiiz"],
        "d": 1,
        "gottesman_form": ["xxxxii"],
        "graph_state": ["i"],
        "group_size_1": 27648.0,
        "group_size_2": 0,
        "is_css": 1,
        "is_decomposable": 0,
        "is_degenerate": 0,
        "is_gf4linear": 0,
        "is_tanner_planar": 1,
        "k": 5,
        "linear_code": ["0"],
        "logicals": ["ixiiii", "iixiii", "iiixii", "iiiixi", "iiiiix", "zziiii", "ziziii", "ziizii", "iiiizi", "iiiiiz"],
        "low_weight_form": ["xxxxii"],
        "n": 6,
        "stabilizer": ["xxxxii"],
        "weight_enumerator": [1, 0, 0, 0, 1, 0, 0]
    },
    "3": {
        "column_swaps": [],
        "css_column_swaps": [],
        "css_form": ["xxxxxi"],
        "css_gottesman_form": ["xxxxxi"],
        "css_logicals": ["ixiiii", "iixiii", "iiixii", "iiiixi", "iiiiix", "zziiii", "ziziii", "ziizii", "ziiizi", "iiiiiz"],
        "d": 1,
        "gottesman_form": ["xxxxxi"],
        "graph_state": ["i"],
        "group_size_1": 23040.0,
        "group_size_2": 0,
        "is_css": 1,
        "is_decomposable": 0,
        "is_degenerate": 0,
        "is_gf4linear": 0,
        "is_tanner_planar": 1,
        "k": 5,
        "linear_code": ["0"],
        "logicals": ["ixiiii", "iixiii", "iiixii", "iiiixi", "iiiiix", "zziiii", "ziziii", "ziizii", "ziiizi", "iiiiiz"],
        "low_weight_form": ["xxxxxi"],
        "n": 6,
        "stabilizer": ["xxxxxi"],
        "weight_enumerator": [1, 0, 0, 0, 0, 1, 0]
    },
    "4": {
        "column_swaps": [],
        "css_column_swaps": [],
        "css_form": ["xxxxxx"],
        "css_gottesman_form": ["xxxxxx"],
        "css_logicals": ["ixiiii", "iixiii", "iiixii", "iiiixi", "iiiiix", "zziiii", "ziziii", "ziizii", "ziiizi", "ziiiiz"],
        "d": 1,
        "gottesman_form": ["xxxxxx"],
        "graph_state": ["i"],
        "group_size_1": 46080.0,
        "group_size_2": 0,
        "is_css": 1,
        "is_decomposable": 0,
        "is_degenerate": 0,
        "is_gf4linear": 0,
        "is_tanner_planar": 1,
        "k": 5,
        "linear_code": ["0"],
        "logicals": ["ixiiii", "iixiii", "iiixii", "iiiixi", "iiiiix", "zziiii", "ziziii", "ziizii", "ziiizi", "ziiiiz"],
        "low_weight_form": ["xxxxxx"],
        "n": 6,
        "stabilizer": ["xxxxxx"],
        "weight_enumerator": [1, 0, 0, 0, 0, 0, 1]
    },
    "5": {
        "column_swaps": [],
        "css_column_swaps": [],
        "css_form": ["xiiiii"],
        "css_gottesman_form": ["xiiiii"],
        "css_logicals": ["ixiiii", "iixiii", "iiixii", "iiiixi", "iiiiix", "iziiii", "iiziii", "iiizii", "iiiizi", "iiiiiz"],
        "d": 1,
        "gottesman_form": ["xiiiii"],
        "graph_state": ["i"],
        "group_size_1": 1866240.0,
        "group_size_2": 0,
        "is_css": 1,
        "is_decomposable": 0,
        "is_degenerate": 0,
        "is_gf4linear": 0,
        "is_tanner_planar": 1,
        "k": 5,
        "linear_code": ["0"],
        "logicals": ["ixiiii", "iixiii", "iiixii", "iiiixi", "iiiiix", "iziiii", "iiziii", "iiizii", "iiiizi", "iiiiiz"],
        "low_weight_form": ["xiiiii"],
        "n": 6,
        "stabilizer": ["xiiiii"],
        "weight_enumerator": [1, 1, 0, 0, 0, 0, 0]
    }
}
